README.rst
setup.py
bin/gitroom
grm/__info__.py
grm/__init__.py
grm/api.py
grm/gr.py
grm/grade.py
grm/img.py
grm/loc.py
grm/utils.py
grm.egg-info/PKG-INFO
grm.egg-info/SOURCES.txt
grm.egg-info/dependency_links.txt
grm.egg-info/not-zip-safe
grm.egg-info/requires.txt
grm.egg-info/top_level.txt