Metadata-Version: 1.1
Name: grm
Version: 0.2.2
Summary: GitRoom Manager: A command line GitHub classroom manager
Home-page: https://github.com/btskinner/grm
Author: Benjamin Skinner
Author-email: b.skinner@vanderbilt.edu
License: MIT
Download-URL: https://github.com/btskinner/grm/archive/grm-v0.2.2.tar.gz
Keywords: github organization classroom manager
Platform: UNKNOWN
Classifier: Development Status :: 4 - Beta
Classifier: License :: OSI Approved :: MIT License
Classifier: Programming Language :: Python :: 3
